Metadata-Version: 2.1
Name: auto-control
Version: 0.9.0
Summary: simples
Home-page: UNKNOWN
Author: dong
Author-email: 15764315865@163.com
License: UNKNOWN
Platform: UNKNOWN
Classifier: Programming Language :: Python :: 3
Classifier: License :: OSI Approved :: MIT License
Classifier: Operating System :: OS Independent
